MANIFEST.in
README.md
setup.py
adhoc/__init__.py
adhoc/glpi_18512.py
bin/check-conf
bin/inv-merge-nbm
bin/inv-per-brand
comring/__init__.py
comring.egg-info/PKG-INFO
comring.egg-info/SOURCES.txt
comring.egg-info/dependency_links.txt
comring.egg-info/not-zip-safe
comring.egg-info/requires.txt
comring.egg-info/top_level.txt
comring/lib/__init__.py
comring/lib/cache.py
comring/lib/clibase.py
comring/lib/config.py
comring/lib/odoo.py
comring/lib/tool.py
comring/tools/__init__.py
comring/tools/finance/__init__.py
comring/tools/finance/do_pfi_value.py
comring/tools/finance/do_total_brand.py
comring/tools/finance/fix_invl_brand.py
comring/tools/finance/inv_total_brand.py
comring/tools/finance/invoice_merge.py
comring/tools/finance/invoice_value.py
comring/tools/finance/validate_invoice.py
comring/tools/hris/__init__.py
comring/tools/hris/je_payroll.py
comring/tools/hris/loaders.py
comring/tools/hris/mappers.py
comring/tools/logistic/__init__.py
comring/tools/logistic/glpi_11132.py
comring/tools/logistic/x.py
comring/tools/sales/__init__.py
comring/tools/sales/get_pricelist.py
comring/tools/sales/get_pricelist2.py
comring/tools/sales/guardian_set_price.py
comring/tools/sales/new_create_inv.py
comring/tools/spinoff/__init__.py
comring/tools/spinoff/bdg_migrate_do_prm.py
comring/webapp/__init__.py
comring/webapp/__main__.py
comring/webapp/auth.py
comring/webapp/config.py
comring/webapp/logging-default.yaml
comring/webapp/main.py
comring/webapp/utils.py
comring/webapp/finance/__init__.py
comring/webapp/finance/invoice.py
comring/webapp/finance/stock_picking.py
comring/webapp/static/favicon.png
comring/webapp/static/css/sb-admin-2.css
comring/webapp/static/css/sb-admin-2.min.css
comring/webapp/static/img/brands-thumb.jpg
comring/webapp/static/img/undraw_posting_photo.svg
comring/webapp/static/js/sb-admin-2.js
comring/webapp/static/js/sb-admin-2.min.js
comring/webapp/static/js/demo/chart-area-demo.js
comring/webapp/static/js/demo/chart-bar-demo.js
comring/webapp/static/js/demo/chart-pie-demo.js
comring/webapp/static/js/demo/datatables-demo.js
comring/webapp/static/scss/_buttons.scss
comring/webapp/static/scss/_cards.scss
