Metadata-Version: 2.1
Name: comring
Version: 0.2.3
Summary: Comring, the PTI ERP companion tool
Home-page: https://github.com/ausuwardi/comring
Author: Agustianes Umbara Suwardi
Author-email: anezch@gmail.com
License: UNKNOWN
Platform: UNKNOWN
Classifier: Programming Language :: Python :: 3
Classifier: License :: OSI Approved :: MIT License
Classifier: Operating System :: OS Independent
